oncapintada/MCMC.py
oncapintada/__init__.py
oncapintada/_version.py
oncapintada/bondcounter.py
oncapintada/bonds_model.py
oncapintada/pair_distribution_function.py
oncapintada/random_mixer.py
oncapintada/sqs.py
oncapintada/sro_binary.py
oncapintada/sro_multicomponent.py
oncapintada/yaml_parser.py
oncapintada-25.11.3.dist-info/METADATA
oncapintada-25.11.3.dist-info/WHEEL
oncapintada-25.11.3.dist-info/licenses/LICENSE
oncapintada-25.11.3.dist-info/RECORD
