Metadata-Version: 2.4
Name: oncapintada
Version: 25.11.3
Summary: Onça-pintada is a python package designed for the analysis and simulation of atomic configurations in materials science.
Project-URL: Homepage, https://github.com/seixasgroup/oncapintada
Author-email: Leandro Seixas <leandro.seixas@proton.me>
License: MIT License
License-File: LICENSE
Classifier: License :: OSI Approved :: MIT License
Classifier: Operating System :: OS Independent
Classifier: Programming Language :: Python :: 3
Classifier: Topic :: Scientific/Engineering :: Chemistry
Classifier: Topic :: Scientific/Engineering :: Physics
Requires-Python: >=3.10
Requires-Dist: ase
Requires-Dist: matplotlib
Requires-Dist: numpy
Requires-Dist: pandas
Requires-Dist: pytest
Requires-Dist: pyyaml
Requires-Dist: scipy
Requires-Dist: torch
